常量池是什么？符号引用和直接引用是什么？

非常好的问题 👍
 这三个概念 —— **常量池（Constant Pool）**、**符号引用（Symbolic Reference）**、**直接引用（Direct Reference）** —— 是理解 JVM 类加载机制、链接过程（Linking）的基础。
 下面我会从「概念 → 在 class 文件中的体现 → 在 JVM 内部的作用 → 举例对比」四个层次帮你彻底搞清楚。

------

## 🧩 一、常量池（Constant Pool）是什么？

### 📘 定义

> 每个 `.class` 文件中都有一个「常量池表（Constant Pool Table）」，
>  存放**编译期生成的各种常量和符号引用信息**，
>  是类加载后建立运行时数据结构的基础。

------

### 💡 类比理解

可以把它理解为：

> “编译阶段 Java 编译器写进 .class 文件里的元数据仓库”。

它是 JVM 理解这个类所需的所有“外部资源引用表”。

------

### 📦 内容包括

| 常量池项类型                               | 示例                            | 含义                 |
| ------------------------------------------ | ------------------------------- | -------------------- |
| 字面量常量（Literals）                     | `"hello"`, `3.14`, `100`        | 编译时就确定的字面值 |
| 类引用（Class）                            | `java/lang/String`              | 当前类引用的类型     |
| 字段引用（Fieldref）                       | `System.out`                    | 指向字段的符号引用   |
| 方法引用（Methodref）                      | `println:(Ljava/lang/String;)V` | 指向方法的符号引用   |
| 接口方法引用（InterfaceMethodref）         | `Comparable.compareTo`          | 接口方法符号引用     |
| 名称与类型描述（NameAndType）              | `(Ljava/lang/String;)V`         | 方法名和签名描述     |
| 动态常量（InvokeDynamic, MethodHandle 等） | `lambda$main$0`                 | 动态调用元数据       |

------

### 🧠 举个例子

```
Test.java
public class Test {
    public static void main(String[] args) {
        String s = "Hello";
        System.out.println(s);
    }
}
```

查看编译后的常量池（`javap -v Test.class`）：

```
Constant pool:
   #1 = Methodref          #7.#20    // java/lang/Object."<init>":()V
   #2 = Fieldref           #21.#22   // java/lang/System.out:Ljava/io/PrintStream;
   #3 = String             #23       // Hello
   #4 = Methodref          #24.#25   // java/io/PrintStream.println:(Ljava/lang/String;)V
   ...
```

可以看到：

- `#2` 表示对字段 `System.out` 的引用；
- `#4` 表示对方法 `PrintStream.println(String)` 的引用；
- 这些都不是直接地址，而是**符号引用（symbolic reference）**。

------

## 🧩 二、符号引用（Symbolic Reference）

### 📘 定义

> 符号引用是在编译期产生的、与内存地址无关的一种“符号化描述”，
>  只记录“类名、字段名、方法名、类型签名”等逻辑标识。

它本质上就是一种「字符串形式的定位信息」。

------

### 💬 举个例子

在常量池中，可能有这样的符号引用：

| 符号引用类型 | 例子                                                | 含义                   |
| ------------ | --------------------------------------------------- | ---------------------- |
| 类符号引用   | `java/lang/String`                                  | 表示要引用这个类       |
| 字段符号引用 | `java/lang/System.out:Ljava/io/PrintStream;`        | 表示要访问这个静态字段 |
| 方法符号引用 | `java/io/PrintStream.println:(Ljava/lang/String;)V` | 表示要调用这个方法     |

它只是告诉 JVM：

> “我需要一个叫 `java/io/PrintStream.println` 的方法，它的签名是 `(Ljava/lang/String;)V`。”

但它**没有内存地址**、没有偏移量。
 JVM 在加载和链接时，会解析这些符号引用为**直接引用**。

------

## 🧩 三、直接引用（Direct Reference）

### 📘 定义

> 直接引用是类加载完成后，JVM 根据符号引用解析出来的**真正运行时指针或句柄**，
>  指向方法区（元空间）中对应的类、方法或字段的具体结构。

换句话说：

- 符号引用 → 逻辑名；
- 直接引用 → 真正的“地址 / 指针”。

------

### 💬 举例说明

| 阶段               | 形式     | 内容                                                         |
| ------------------ | -------- | ------------------------------------------------------------ |
| 编译期             | 符号引用 | `"java/io/PrintStream.println:(Ljava/lang/String;)V"`        |
| 链接期（解析阶段） | 直接引用 | 指向方法区中 `PrintStream.println()` 的 `Method*` 结构体地址 |

因此，当代码执行：

```java
System.out.println("Hello");
```

时：

1. 字节码中指令 `invokevirtual #4` → 常量池索引；
2. 常量池索引 #4 是一个符号引用；
3. 链接解析时 JVM 找到实际的 `Method*`；
4. 替换为直接引用；
5. 执行调用。

------

## 🧩 四、类加载和符号解析的过程

类加载过程：

```
加载（Loading）
→ 链接（Linking）
    → 验证（Verify）
    → 准备（Prepare）
    → 解析（Resolve） ← 在这里把符号引用转为直接引用
→ 初始化（Initialize）
```

📍 在“解析（Resolve）”阶段：

- JVM 遍历常量池里的符号引用；
- 通过 `ClassLoader` 加载目标类；
- 查找对应的字段、方法、接口；
- 生成直接引用（指针）；
- 替换常量池项。

------

## 🧠 五、类比总结

| 对象         | 阶段             | 示例                   | 比喻                |
| ------------ | ---------------- | ---------------------- | ------------------- |
| **符号引用** | 编译期生成       | `"java/lang/String"`   | 「人名」            |
| **直接引用** | 运行期解析       | 指针 → String 类元信息 | 「身份证号 + 住址」 |
| **常量池**   | 存放所有符号引用 | 包含名字表和引用表     | 「通讯录」          |

------

## ✅ 六、总结一句话

> **常量池**：类文件中的“符号引用仓库”；
>  **符号引用**：逻辑名称（编译期产生，不含地址）；
>  **直接引用**：JVM 运行时根据符号引用解析得到的真实地址或句柄。

------

是否希望我帮你画一张图，展示“常量池中符号引用 → 类加载时解析成直接引用 → 运行时方法调用”的完整流程（包括方法区结构和内存地址指向）？那张图看一眼就能把三个概念的关系彻底理解透。

<div style="height:10px; background:linear-gradient(to right, #ff6a00, #ee0979, #00c6ff); border:none;"></div>

Constant pool:  
   #1 = Methodref          #7.#20    // java/lang/Object."<init>":()V  
   #2 = Fieldref           #21.#22   // java/lang/System.out:Ljava/io/PrintStream;  
   #3 = String             #23       // Hello  
   #4 = Methodref          #24.#25   // java/io/PrintStream.println:(Ljava/lang/String;)V  
   ...明白意思和作用了，但是这里没看懂这些数字啥意思

非常好 👍 你现在已经真正理解了常量池的“内容和用途”，
 剩下的这些数字其实就是 **常量池的索引和引用关系** —— 是 JVM 在 `.class` 文件中组织这些常量的一种方式。
 我们来逐层讲清楚你看到的这些编号代表什么。

------

## 🧩 一、先看整体结构

在 `.class` 文件中，常量池（constant pool）是一个**表结构**：

```text
constant_pool_count
constant_pool[constant_pool_count - 1]
```

- 每个常量项都有一个编号，从 **#1 开始**（#0 不用，保留）。
- 所有的 `#数字` 就是常量池表的**索引**。
- 某些常量池项会引用其他项，于是形成像 `#7.#20` 这样的“层级索引关系”。

你可以把它想成一个“数组”，只不过元素类型不同。

------

## 🧠 二、你的例子逐条解释

```
#1 = Methodref          #7.#20    // java/lang/Object."<init>":()V
#2 = Fieldref           #21.#22   // java/lang/System.out:Ljava/io/PrintStream;
#3 = String             #23       // Hello
#4 = Methodref          #24.#25   // java/io/PrintStream.println:(Ljava/lang/String;)V
```

------

### ✅ #1 解释：`Methodref #7.#20`

| 部分        | 含义                                                         |
| ----------- | ------------------------------------------------------------ |
| `#1`        | 这是常量池的第 1 项                                          |
| `Methodref` | 表示“方法引用”类型的常量（CONSTANT_Methodref）               |
| `#7`        | 指向一个 **Class** 类型常量（class 引用），描述方法所属的类，即 `java/lang/Object` |
| `#20`       | 指向一个 **NameAndType** 类型常量，描述方法名 + 方法描述符（参数与返回值），即 `"<init>":()V` |
| 译义        | 表示调用 `java/lang/Object` 的构造方法 `Object()`            |

------

### ✅ #2 解释：`Fieldref #21.#22`

| 部分       | 含义                                              |
| ---------- | ------------------------------------------------- |
| `#2`       | 常量池第 2 项                                     |
| `Fieldref` | 表示字段引用                                      |
| `#21`      | 指向类常量（Class），`java/lang/System`           |
| `#22`      | 指向 NameAndType，`out:Ljava/io/PrintStream;`     |
| 译义       | 表示访问字段 `System.out`，其类型是 `PrintStream` |

------

### ✅ #3 解释：`String #23`

| 部分     | 含义                         |
| -------- | ---------------------------- |
| `#3`     | 常量池第 3 项                |
| `String` | 表示一个字符串常量引用       |
| `#23`    | 指向一个 UTF8 常量 `"Hello"` |
| 译义     | 表示字符串字面量 `"Hello"`   |

------

### ✅ #4 解释：`Methodref #24.#25`

| 部分        | 含义                                                   |
| ----------- | ------------------------------------------------------ |
| `#4`        | 常量池第 4 项                                          |
| `Methodref` | 表示方法引用                                           |
| `#24`       | 指向类常量（Class），`java/io/PrintStream`             |
| `#25`       | 指向 NameAndType 常量，`println:(Ljava/lang/String;)V` |
| 译义        | 表示调用方法 `PrintStream.println(String)`             |

------

## 🧩 三、那 #7、#20、#21、#22、#23、#24、#25 又是什么？

它们其实在下面常量池中会单独出现，类似：

```
#7  = Class              #8        // java/lang/Object
#8  = Utf8               java/lang/Object

#20 = NameAndType        #9:#10    // "<init>":()V
#9  = Utf8               <init>
#10 = Utf8               ()V

#21 = Class              #11       // java/lang/System
#11 = Utf8               java/lang/System

#22 = NameAndType        #12:#13   // out:Ljava/io/PrintStream;
#12 = Utf8               out
#13 = Utf8               Ljava/io/PrintStream;

#23 = Utf8               Hello

#24 = Class              #14       // java/io/PrintStream
#14 = Utf8               java/io/PrintStream

#25 = NameAndType        #15:#16   // println:(Ljava/lang/String;)V
#15 = Utf8               println
#16 = Utf8               (Ljava/lang/String;)V
```

------

## 🧠 四、层级结构总结图

可以理解为下面这种树状关系：

```
#1 Methodref → (#7 Class → (#8 Utf8 java/lang/Object))
               (#20 NameAndType → (#9 Utf8 <init>, #10 Utf8 ()V))

#2 Fieldref  → (#21 Class → (#11 Utf8 java/lang/System))
               (#22 NameAndType → (#12 Utf8 out, #13 Utf8 Ljava/io/PrintStream;))

#3 String    → (#23 Utf8 Hello)

#4 Methodref → (#24 Class → (#14 Utf8 java/io/PrintStream))
               (#25 NameAndType → (#15 Utf8 println, #16 Utf8 (Ljava/lang/String;)V))
```

可以看到：

- `Methodref` / `Fieldref` 只是“顶层符号引用项”；
- 它们再通过数字引用指向更底层的常量；
- 最底层一定是 `Utf8`（真正的字符串字面值）。

------

## 🧩 五、这些索引如何被字节码使用？

字节码指令中也会引用这些常量池索引：

```
getstatic #2   // 从常量池取 System.out
ldc #3          // 从常量池取字符串 "Hello"
invokevirtual #4 // 调用 println 方法
```

这就是为什么常量池编号非常重要 ——
 **字节码执行时通过编号找到对应的常量池项，再解析成符号引用，然后再解析成直接引用。**

------

## ✅ 六、总结一句话

| 概念                       | 含义                               |
| -------------------------- | ---------------------------------- |
| `#数字`                    | 常量池表的索引编号                 |
| 左边的标识（如 Methodref） | 常量项类型                         |
| `#a.#b`                    | 指向其他常量池项的引用关系         |
| `//` 注释部分              | 已解析的友好可读形式（供人类查看） |

------

📘 **一句话记忆：**

> 常量池就是一张“索引表”，`#数字` 是条目号，
>  每个条目可能再引用其他条目，最终指向 `Utf8` 字符串形成一棵描述结构树。

------

是否希望我帮你画一张完整的「常量池索引关系图」（像 AST 一样展开 `Methodref` → `Class` → `Utf8`）？
 那张图能让你一眼看到每个数字之间是怎么层层引用的。

<div style="height:10px; background:linear-gradient(to right, #ff6a00, #ee0979, #00c6ff); border:none;"></div>

理解了，这么说符合引用转为直接引用时会将常量池中的外部引用项转为地址吗？那方法指令中的索引是不是不用变？

🌟非常棒，你已经完全理解到 **JVM 链接阶段（Linking → Resolve）** 的核心本质了。
 你问的这两个问题实际上正中 JVM 的关键机制，我们逐层解析，让你彻底理解“解析（Resolution）”到底做了什么。

------

## 🧩 一、你的理解完全正确 ✅

> 在**符号引用转为直接引用**时，JVM 会把常量池中代表“外部引用”的项（如类、字段、方法）
>  **解析成运行时的直接引用（指针/句柄）**。

也就是说：

- `.class` 文件里的常量池项原本是 **字符串形式的逻辑描述**（如 `"java/lang/String"`）；
- 加载后 JVM 会在 **运行时常量池（Runtime Constant Pool）** 中
   把它“解析”为指向方法区中类、方法、字段等结构的 **真实地址引用**。

------

## 🧠 二、那“方法指令中的索引”会不会变？

不变！

这是关键点 👇

> **字节码指令中对常量池的索引（#n）永远不变。**
>
> 在解析之后，JVM 会把常量池对应的槽位内容替换为“直接引用”，
>  这样字节码中仍然使用相同的索引值，只是它所指向的内容变了。

------

### 📘 举例说明

以 `invokevirtual #4` 为例：

1. **初始状态（加载后、未解析）**

   - 常量池第 4 项类型是 `CONSTANT_Methodref`
   - 内容：`java/io/PrintStream.println:(Ljava/lang/String;)V`（符号引用）
   - 字节码指令中写着：`invokevirtual #4`

2. **解析后（Resolve 阶段）**

   - JVM 遍历常量池，找到第 4 项；
   - 通过类加载器加载目标类 `java/io/PrintStream`；
   - 查找其方法表中的 `println(String)`；
   - 创建或缓存一个 `Method*` 指针；
   - 将常量池槽位 #4 的内容替换为指向该 `Method*` 的直接引用。

   🧩 结果：

   ```
   constant_pool[4] = MethodRef { resolved = true, value = pointer to Method* }
   ```

3. **执行阶段（运行时）**

   - 当执行到 `invokevirtual #4` 时，
      JVM 不再重新查字符串，而是直接从常量池槽 #4 拿到已解析的 `Method*` 地址，直接跳转。

⚙️ 所以：

> ✅ 指令里的 `#4` **不变**；
>  🔁 但常量池第 4 项的内容从“符号信息”变成了“地址引用”。

------

## 🧩 三、JVM 为什么设计成“索引不变 + 槽内容可替换”？

这是一种高效且线程安全的优化机制。

| 原因             | 解释                                                         |
| ---------------- | ------------------------------------------------------------ |
| 💡 **节省空间**   | 字节码只需存一个 `#index`，不用每次存长字符串。              |
| ⚡ **加速解析**   | 常量池项可缓存解析结果；指令不需要改动。                     |
| 🧱 **结构稳定**   | 常量池索引是固定编号，加载解析过程不会破坏指令流。           |
| 🔒 **多线程安全** | 解析可以惰性完成（lazy resolution），每个常量项可标记“已解析”。 |

------

## 🧩 四、过程对比（符号引用 → 直接引用）

| 阶段               | 常量池项内容                                          | 指令索引 | 行为                 |
| ------------------ | ----------------------------------------------------- | -------- | -------------------- |
| 类加载后（未解析） | `"java/io/PrintStream.println:(Ljava/lang/String;)V"` | `#4`     | 逻辑描述（符号引用） |
| 链接解析后         | 指向方法区中 `Method*` 的指针                         | `#4`     | 直接引用             |
| 执行时             | 直接取出 Method 指针                                  | `#4`     | 调用目标方法         |

------

## 🧠 五、延伸：懒解析（Lazy Resolution）

JVM 实际上**不会一次性解析所有符号引用**。
 而是采用“**按需解析**”策略：

- 当第一次执行某条引用指令（如 `getstatic #2`, `invokevirtual #4`）时；
- 如果常量池项未解析；
- JVM 就在那一刻解析并缓存；
- 之后的访问都是直接引用。

👉 这称为 **懒解析（Lazy Resolution）**，避免不必要的开销。

------

## ✅ 六、总结一句话

> - 常量池中的 `#编号` 永远固定，对应字节码中使用的索引；
> - 解析阶段会把这些编号对应的常量项，从“符号引用（字符串）”替换为“直接引用（指针）”；
> - 指令执行时仍用同样的索引号，但查到的内容已经是地址。

------

## 💡 类比记忆

| 阶段   | 常量池内容                 | 比喻                   |
| ------ | -------------------------- | ---------------------- |
| 编译时 | `"张三, 北京, 电话号未知"` | 符号引用：仅文字描述   |
| 链接后 | 指向张三的身份证号         | 直接引用：真实唯一标识 |
| 执行时 | 用身份证号找到张三本人     | 直接访问运行时对象     |

------

是否希望我帮你画一张图，把「字节码指令 → 常量池索引 → 符号引用 → 解析后指针 → 运行时调用」整个流程串起来？
 那张图能让你清楚看到 `#index` 永远不变，而常量池内容如何逐步替换成“地址引用”。

<div style="height:10px; background:linear-gradient(to right, #ff6a00, #ee0979, #00c6ff); border:none;"></div>

如果用到一个别的对象中的字段，常量池中应该是#x.#y,#x解析后会成对象的地址，那#y是这个字段在堆区对象中的地址，还是直接是这个变量值？

💯 非常棒的问题！
 你现在已经走到了 **JVM 符号引用解析** 的最细节层面 ——
 问得非常专业，而且正中 **“字段引用的解析结果到底是什么”** 这个常被忽略的核心点。

我们来系统讲清楚：
 当字节码要访问一个“别的对象的字段”时，常量池中的 `#x.#y` 解析后到底对应什么？
 `#x` 解析成什么？`#y` 又指向什么？
 它们在 JVM 内部分别对应不同层级的“元信息”和“运行时实例”。

------

## 🧩 一、先回顾常量池里字段引用的结构

在 `.class` 文件中，一个字段引用（`Fieldref`）的结构是：

```
Fieldref_info {
    u1 tag; // = 9
    u2 class_index;       // 指向 CONSTANT_Class
    u2 name_and_type_index; // 指向 CONSTANT_NameAndType
}
```

举例（`javap -v` 输出）：

```
#2 = Fieldref  #21.#22  // java/lang/System.out:Ljava/io/PrintStream;
#21 = Class             #11 // java/lang/System
#22 = NameAndType       #12:#13 // out:Ljava/io/PrintStream;
```

意思是：

> 符号引用表示 “类 java/lang/System 中的字段 out，它的类型是 java/io/PrintStream”。

------

## 🧠 二、解析阶段发生什么？

在 **类加载链接的解析阶段（Linking → Resolve）**，
 JVM 会将符号引用解析为一个 **运行时直接引用**。
 但注意，这里的“直接引用”并不是“字段的内存地址”，
 而是 **指向字段元数据结构（FieldDescriptor / FieldInfo / FieldOffset）** 的引用。

### 🔹 解析步骤

1. **解析 `#x`（Class 部分）**
   - JVM 会通过类加载器加载 `java/lang/System`；
   - 得到一个类元数据结构 `InstanceKlass*`；
   - 并缓存这个指针。
2. **解析 `#y`（NameAndType 部分）**
   - JVM 会查找该类的字段表（`InstanceKlass::_fields`）；
   - 根据字段名 `"out"` 和描述符 `"Ljava/io/PrintStream;"`；
   - 找到对应的字段元信息（FieldInfo）；
   - 获取字段在对象实例或静态区的**偏移量（field offset）**；
   - 生成一个指向该字段元信息的直接引用（非堆中变量值）。

------

## ⚙️ 三、那么解析后存的是什么？

| 层级                       | 含义          | 存的是什么                                               |
| -------------------------- | ------------- | -------------------------------------------------------- |
| `#x`                       | 类引用        | 指向方法区（Metaspace）中目标类的 `InstanceKlass*`       |
| `#y`                       | 字段名+描述符 | 在解析后转化为 `FieldInfo*` 或字段偏移量（field offset） |
| 常量池项整体（`Fieldref`） | 字段引用项    | 指向 `(InstanceKlass*, FieldInfo*)` 的结构体句柄         |

也就是说：

> 常量池的 `Fieldref` 在解析后，得到的是“类 + 字段元信息”的直接引用，
>  并不是字段的“堆内存地址”或“变量值”。

------

## 🧩 四、访问字段时才会去“对象实例”里取值

关键点 ⚠️：

> 解析出的“字段引用”只是找到**字段定义在哪个类、偏移是多少**，
>  真正去堆区取字段值是在 **执行指令时** 才发生的。

例如：

### 示例

```java
System.out.println(obj.value);
```

对应字节码：

```
getstatic  #2 // System.out
aload_1        // 加载 obj
getfield  #5  // obj.value
invokevirtual #6 // println
```

逐步过程：

1. `getstatic #2`
   - 常量池 #2 是一个 `Fieldref`（`System.out`）；
   - 已解析为 `(Klass java/lang/System, FieldInfo out)`；
   - JVM 从类元信息里根据字段偏移找到静态区内存，取出 `out` 对象引用；
   - 结果放入操作数栈：一个指向堆中 `PrintStream` 实例的引用。
2. `aload_1`
   - 把局部变量表中的 `obj` 压栈。
3. `getfield #5`
   - 常量池 #5 是 `Fieldref`（`Example.value`）；
   - 已解析为 `(Klass Example, FieldInfo value)`；
   - JVM 从栈顶弹出 `obj` 引用；
   - 根据 `FieldInfo` 的偏移量，在堆中 `obj` 的对象布局中找到该字段位置；
   - 取出字段的 **值（primitive）或引用（object ref）**；
   - 压栈。

⚙️ 所以：

> 只有在执行 `getfield` / `putfield` / `getstatic` / `putstatic` 时，
>  JVM 才会根据常量池项中的偏移信息去真正的堆内取值。

------

## 🧠 五、为什么不能是字段值或堆地址？

1. **字段值是随对象不同而不同的**，常量池是类级共享结构，不可能为每个对象存一个。
2. **堆地址会变化**（GC 压缩、移动），JVM 不会把堆地址硬编码到常量池里。
3. 因此常量池只存**元数据 + 偏移量**，访问时才根据实例引用计算实际地址。

------

## 🧩 六、总结图示

```
常量池中：
#5 = Fieldref #7.#12  // com/example/MyClass.value:I

解析后：
Fieldref[#5] = {
    class_ref  → InstanceKlass*(com/example/MyClass)
    field_ref  → FieldInfo*(name="value", offset=12)
}

执行 getfield #5 时：
1. 弹出对象引用 obj
2. obj_addr + field.offset = value_addr
3. 从堆中读取对应值
```

------

## ✅ 七、总结一句话

| 内容                   | 解释                                                   |
| ---------------------- | ------------------------------------------------------ |
| `#x`                   | 类引用，解析成类元数据地址（InstanceKlass*）           |
| `#y`                   | 字段名+类型，解析成字段描述符（FieldInfo），包含偏移量 |
| 常量池中 Fieldref      | 解析成 `(类信息 + 字段偏移)` 的直接引用                |
| 真正字段值             | 在执行阶段通过对象引用和偏移量计算得到                 |
| 不会存放堆地址或变量值 | 因为字段值属于对象，常量池属于类                       |

------

✅ **一句话记忆：**

> 字段引用解析后拿到的不是“堆里的数据”，
>  而是“如何找到那块数据”的**元信息 + 偏移量**，
>  真正取值要等执行 `getfield` 指令时，根据对象引用去堆中取。

------

是否希望我帮你画一张图（带堆、方法区、常量池、操作数栈），
 直观展示一次 `getfield` 执行过程：从常量池引用 → 解析成偏移 → 从堆对象取值？