对象成员赋值和非静态代码块会合并到init方法中吗？

非常棒 👍 你问的这个问题是 **理解 Java 对象初始化过程的关键点**——
 “实例成员赋值”和“非静态代码块”是否会被合并到 `<init>` 构造方法中。
 答案是：

> ✅ **是的，它们会被编译器合并进每个构造方法（即 `<init>` 方法）中执行。**
>
> JVM 层面上，`<init>` 方法就是构造方法（constructor），
>  所有的**实例字段赋值语句**和**非静态代码块**最终都会编译进这个方法。

下面我们通过解释 + 实例 + 字节码分析来彻底说明这个机制。

------

## 🧩 一、类中“初始化逻辑”的几种类型

在一个普通 Java 类中，初始化代码可以分为：

| 类型         | 执行时机   | 编译后归属 | 示例                               |
| ------------ | ---------- | ---------- | ---------------------------------- |
| 静态变量赋值 | 类加载时   | `<clinit>` | `static int a = 1;`                |
| 静态代码块   | 类加载时   | `<clinit>` | `static { ... }`                   |
| 实例变量赋值 | 对象创建时 | `<init>`   | `int x = 10;`                      |
| 非静态代码块 | 对象创建时 | `<init>`   | `{ System.out.println("block"); }` |
| 构造方法体   | 对象创建时 | `<init>`   | `Test() { ... }`                   |

------

## 🧠 二、为什么会“合并”到 `<init>` 方法中

JVM 层面只认识两种初始化方法：

| 方法名     | 作用                                               |
| ---------- | -------------------------------------------------- |
| `<clinit>` | 类的静态初始化（静态变量 + 静态块）                |
| `<init>`   | 对象的实例初始化（实例变量 + 非静态块 + 构造方法） |

也就是说，Java 编译器在编译阶段会把：

- 每个实例字段的初始化语句；
- 每个非静态代码块；
- 再加上构造方法本身；

**全部按顺序拼接进 `<init>` 构造方法的字节码中。**

------

## ⚙️ 三、编译示例验证

```java
public class Test {
    int a = 10;                // 实例字段赋值
    int b;

    {                          // 非静态代码块
        b = 20;
        System.out.println("block");
    }

    public Test() {            // 构造方法
        System.out.println("constructor");
    }
}
```

编译后（`javap -c Test.class`）：

```text
public Test();
  Code:
     0: aload_0
     1: invokespecial #1                  // 调用 Object.<init>()
     4: aload_0
     5: bipush        10
     7: putfield      #2                  // this.a = 10
    10: aload_0
    11: bipush        20
    13: putfield      #3                  // this.b = 20
    16: getstatic     #4                  // System.out
    19: ldc           #5                  // "block"
    21: invokevirtual #6                  // println("block")
    24: getstatic     #4
    27: ldc           #7                  // "constructor"
    29: invokevirtual #6                  // println("constructor")
    32: return
```

可以看到 `<init>` 方法的执行顺序：

| 步骤  | 字节码             | 含义                     |
| ----- | ------------------ | ------------------------ |
| 0–1   | 调用父类构造方法   | `super()`                |
| 4–7   | 执行实例字段初始化 | `this.a = 10`            |
| 10–21 | 执行非静态代码块   | 设置 b=20 并打印 "block" |
| 24–29 | 执行构造方法体     | 打印 "constructor"       |

👉 说明编译器确实把“实例变量赋值 + 非静态块 + 构造方法体”**合并进了 `<init>`**。

------

## 🧠 四、顺序规则（重点记住）

在 **每个构造方法** 中，执行顺序固定如下：

1. **调用父类构造方法**（必须在第一行）；
2. **执行本类的实例变量赋值语句**；
3. **执行本类的非静态代码块**；
4. **执行当前构造方法体**。

所以对于：

```java
class A {
    int x = f();         // (2)
    { g(); }             // (3)
    A() { h(); }         // (4)
}
```

JVM 实际运行顺序是：

```
(1) 调用 super.<init>()
(2) 执行 this.x = f()
(3) 执行 g()
(4) 执行 h()
```

------

## 🧱 五、扩展：多个构造方法的情况

假设：

```java
public class Test {
    int x = init();

    { System.out.println("block"); }

    public Test() {
        System.out.println("no-arg");
    }

    public Test(int n) {
        System.out.println("arg");
    }

    private int init() {
        System.out.println("field init");
        return 1;
    }
}
```

编译后你会看到：

- 会生成两个 `<init>` 方法；
- 每个 `<init>` 方法都包含 **字段初始化** + **非静态块**；
- 然后再拼上对应构造体的内容。

也就是说：

> 每个构造方法都会重复包含这些通用的实例初始化逻辑。

------

## 📦 六、静态成员的区别

静态字段初始化和静态代码块则会被编译进 `<clinit>` 方法，只执行一次：

```java
class Test {
    static int a = 10;
    static { System.out.println("static"); }
}
```

编译后有 `<clinit>`：

```
0: bipush        10
2: putstatic     #2                  // a = 10
5: getstatic     #3                  // System.out
8: ldc           #4                  // "static"
10: invokevirtual #5
13: return
```

------

## ✅ 七、总结

| 初始化内容   | 执行时机     | 编译后所在方法 | 执行次数     | 合并情况             |
| ------------ | ------------ | -------------- | ------------ | -------------------- |
| 静态变量赋值 | 类加载时     | `<clinit>`     | 1 次         | 合并到 `<clinit>`    |
| 静态代码块   | 类加载时     | `<clinit>`     | 1 次         | 合并到 `<clinit>`    |
| 实例变量赋值 | 每次创建对象 | `<init>`       | 每次构造调用 | 合并到 `<init>`      |
| 非静态代码块 | 每次创建对象 | `<init>`       | 每次构造调用 | 合并到 `<init>`      |
| 构造方法体   | 每次创建对象 | `<init>`       | 每次构造调用 | 紧跟在前两者之后执行 |

------

📘 **一句话总结：**

> 实例成员赋值语句和非静态代码块的字节码，
>  都被编译器合并进每个构造方法 (`<init>`) 中，
>  并且按「父类构造 → 实例字段 → 非静态块 → 构造体」的顺序执行。

======
如果在构造器中调用别的构造器呢？
非常好的问题 👍！
你现在问的是 Java 构造器链（constructor chaining）的问题，也就是：

> 当一个构造器里调用另一个构造器（通过 `this(...)`）时，
> 实例变量赋值、非静态代码块、构造器体之间的执行顺序会发生什么变化？

我们来用 **编译器视角（字节码）+ 执行顺序图** 来彻底搞清楚这一点。

---

## 🧩 一、问题示例

```java
public class Test {
    int a = initA();

    { System.out.println("block"); }

    Test() {
        this(10); // 调用另一个构造器
        System.out.println("no-arg");
    }

    Test(int x) {
        System.out.println("arg");
    }

    int initA() {
        System.out.println("field init");
        return 1;
    }
}
```

你想知道的是：

> 当执行 `new Test()` 时，执行顺序是什么？
> 字段初始化、代码块、两个构造器的体，会不会执行两遍？

---

## ✅ 二、结论先行（最重要的规律）

> 在 Java 中，**无论调用多少个构造器（this(...) 调用链）**，
> 👉 实例字段赋值语句 和 非静态代码块 **只会执行一次**。
>
> 它们在整个构造链的“最开始”阶段，由**最终被调用的那个构造器**负责执行。

---

## 🧠 三、逐步分析执行过程

执行 `new Test()` 时，JVM 的真实过程如下：

1. **分配对象内存**（所有实例字段默认 0 / null）
2. **调用最外层构造器 `Test()`**
3. 在 `Test()` 构造器的第一行发现 `this(10)`：

   * 暂停当前构造器；
   * 转去调用另一个构造器 `Test(int x)`；
4. **在调用 `Test(int)` 前**，编译器会插入：

   * 父类构造方法调用（`super()`）；
   * 实例字段初始化；
   * 非静态代码块；
5. 然后执行 `Test(int)` 构造器体；
6. 返回到 `Test()` 构造器继续执行剩余代码。

---

## 🧩 四、我们来看真实输出

运行上面的代码：

```java
new Test();
```

输出结果：

```
field init
block
arg
no-arg
```

顺序解释如下：

| 步骤 | 执行内容         | 说明                         |
| -- | ------------ | -------------------------- |
| 1  | `field init` | 实例变量初始化执行（只一次）             |
| 2  | `block`      | 非静态代码块执行（只一次）              |
| 3  | `arg`        | 先调用的那个目标构造器（`this(10)`) 执行 |
| 4  | `no-arg`     | 回到原始构造器执行剩余代码              |

---

## ⚙️ 五、编译器在背后做了什么（字节码视角）

编译后生成两个 `<init>` 方法：

### （1）无参构造器 `<init>()`

```text
0: aload_0
1: invokespecial #1                // 调用 Object.<init>()
4: aload_0
5: bipush 10
7: invokespecial #2                // 调用 Test(int)
10: getstatic #3                   // System.out
13: ldc #4                         // "no-arg"
15: invokevirtual #5               // println
18: return
```

### （2）有参构造器 `<init>(I)`

```text
0: aload_0
1: invokespecial #1                // 调用 Object.<init>()
4: aload_0
5: invokevirtual #6                // 调用 this.initA()
8: putfield #7                     // this.a = ...
11: getstatic #3
14: ldc #8                         // "block"
16: invokevirtual #5
19: getstatic #3
22: ldc #9                         // "arg"
24: invokevirtual #5
27: return
```

观察关键点 👇：

* 实例字段赋值 (`this.a = ...`) 和 非静态块（`block`）都被编译进 **`<init>(int)`**；
* 而 `<init>()` 构造器中只是直接调用 `<init>(int)`；
* 所以它不会再次执行初始化逻辑。

---

## 🧩 六、规律总结

| 构造器调用形式                  | 字节码生成                     | 实例变量 / 非静态块执行次数 |
| ------------------------ | ------------------------- | --------------- |
| 只定义一个构造器                 | 每次 `new` 调用都会执行一次         | ✅ 1 次           |
| 构造器 A 调用构造器 B（this(...)） | 编译器把初始化逻辑放进“最底层”构造器 B 中   | ✅ 1 次           |
| 构造器链（this(...) 多级调用）     | 初始化逻辑在最后被调用的那一个构造器里执行     | ✅ 1 次           |
| 继承关系（super(...)）         | 父类 `<init>` 执行完 → 子类字段初始化 | 各类独立执行一次        |

---

## 🧩 七、和 `super(...)` 的区别

| 调用形式         | 初始化执行方      | 是否重复               |
| ------------ | ----------- | ------------------ |
| `this(...)`  | 同一个类的另一个构造器 | ❌ 只执行一次（放在最底层）     |
| `super(...)` | 父类构造器       | ✅ 父类、子类各执行一次自己的初始化 |

📘 **简记：**

> `this(...)`：同级构造器调用，实例初始化逻辑只执行一次；
> `super(...)`：跨类调用，父类和子类各自执行一次各自的初始化逻辑。

---

## ✅ 八、总结一句话

> **在 Java 中，实例字段赋值语句与非静态代码块始终只执行一次。**
> 它们会被编译器放到每个构造器调用链的“最底层构造器”中执行。
>
> 当一个构造器通过 `this(...)` 调用另一个构造器时，
> 初始化逻辑不会重复执行，而只在第一次进入构造器链底端时运行。

---

是否希望我帮你画一张“构造器调用链执行顺序图”（带箭头，显示 super → this 调用路径、各层 init 执行顺序）？那张图能让你一眼看懂「this 调用链」和「super 调用链」的区别。
