迭代器与内部类

java中成员内部类在编译后内部会有外部类的字段吗？

非常好的问题，这其实是理解 **Java 内部类编译机制** 的关键点。我们来仔细说明：

------

### 🧩 结论：**是的，成员内部类在编译后会包含一个指向外部类实例的“合成字段（synthetic field）**。

也就是说：

> 成员内部类（非 static）在字节码层面上，会被编译器自动添加一个 **指向外部类对象的引用**。

------

### 📘 举个例子

```java
public class Outer {
    private int x = 10;

    public class Inner {
        public void show() {
            System.out.println("x = " + x);
        }
    }
}
```

编译后会生成两个 `.class` 文件：

```
Outer.class
Outer$Inner.class
```

查看 `Outer$Inner.class`（使用 `javap -p Outer$Inner.class`）可以看到类似内容：

```
class Outer$Inner {
  final Outer this$0; // 👈 编译器自动生成的字段

  Outer$Inner(Outer outer) { // 构造函数隐式传入外部类实例
      this.this$0 = outer;
  }

  public void show();
}
```

------

### 🧠 解释：

- **`this$0` 字段**：是编译器生成的一个合成字段（synthetic field），用来保存创建该内部类实例时所关联的外部类对象引用。

- 当你写：

  ```java
  Outer outer = new Outer();
  Outer.Inner inner = outer.new Inner();
  ```

  编译器会隐式地执行：

  ```java
  new Outer$Inner(outer);
  ```

  也就是把 `outer` 传进 `this$0` 字段。

------

### ⚙️ 为什么需要这个字段？

因为非静态内部类（`Inner`）需要能访问外部类的非静态成员（如 `x`），而这种访问在底层其实是通过：

```java
this$0.x
```

来实现的。

------

### 🧩 对比：静态内部类

如果你改成：

```java
public static class Inner { ... }
```

此时编译后的字节码中：

- **不会再有 `this$0` 字段**
- 因为静态内部类与外部类实例无关，不需要外部类对象引用

------

### ✅ 小结

| 类型                    | 是否持有外部类引用 | 是否生成 `this$0` 字段           |
| ----------------------- | ------------------ | -------------------------------- |
| 非静态成员内部类        | ✅ 是               | ✅ 有                             |
| 静态内部类              | ❌ 否               | ❌ 无                             |
| 局部内部类 / 匿名内部类 | ✅ 是               | ✅ 有（对应的合成字段可能名不同） |

------

如果你愿意，我可以帮你画一张 JVM 层级示意图，展示：

- 外部类对象
- 内部类对象
- 内部类如何通过 `this$0` 引用访问外部类字段

是否要我画这张图？

<div style="height:8px; border:none; border-radius:4px;
background:linear-gradient(90deg, #0f2027, #203a43, #2c5364);">
</div>

show()方法在编译后参数会有这两个内外类对象吗？

非常好的问题 👏——你问的其实是 **Java 编译器在成员内部类中如何传递“外部类实例”引用给方法（尤其是非静态方法）**。

我们来**一步步拆解**这个问题。

------

## 🔍 问题重述

你问的是：

> 在成员内部类的 `show()` 方法中，编译后是不是方法签名会有“内外类对象”作为参数？

------

## ✅ 简短回答

> **不会直接在 `show()` 方法参数中出现外部类对象。**
>
> 外部类对象会以 **合成字段（`this$0`）** 的形式存储在内部类实例中，而不是作为方法参数传入。
>
> 调用 `inner.show()` 时，实际上是通过内部类的 `this`（其中包含了对外部类的引用）间接访问外部类成员。

------

## 📘 举个例子

```java
public class Outer {
    private int x = 10;

    public class Inner {
        public void show() {
            System.out.println("x = " + x);
        }
    }
}
```

我们编译后执行：

```bash
javac Outer.java
javap -p Outer$Inner.class
```

输出大致如下（简化版）：

```java
class Outer$Inner {
  final Outer this$0; // 👈 外部类引用字段

  Outer$Inner(Outer outer) { // 构造函数参数才有外部类对象
      this.this$0 = outer;
  }

  public void show(); // 👈 没有额外参数
}
```

------

## 🧩 show() 的字节码细节

查看 `javap -c -p Outer$Inner` 的结果（核心部分）：

```
public void show();
  Code:
     0: getstatic     #2  // Field java/lang/System.out:Ljava/io/PrintStream;
     3: aload_0        // 加载 this（Inner 对象）
     4: getfield       #3  // Field this$0:LOuter;
     7: getfield       #4  // Field Outer.x:I
    10: invokevirtual  #5  // Method java/io/PrintStream.println:(I)V
    13: return
```

解释：

1. `aload_0` → 取当前 `Inner` 实例 (`this`)
2. `getfield this$0` → 从当前实例中取出外部类引用 (`Outer`)
3. `getfield Outer.x` → 读取外部类的私有字段 `x`
4. 打印它

🔹 可以看到：

- `show()` 方法签名并没有额外参数。
- 访问外部类字段时，是通过 `this$0` 间接访问的。

------

## ⚙️ 对比构造函数

**构造函数才有“外部类对象”作为参数**：

```
Outer$Inner(Outer outer)
```

这是因为在创建 `Inner` 实例时，编译器会自动传入外部类引用：

```java
Outer outer = new Outer();
Outer.Inner inner = outer.new Inner();
// 实际是 new Outer$Inner(outer)
```

这个 `outer` 参数会被赋值给 `this$0`，之后所有内部方法通过它访问外部类成员。

------

## 🧠 总结表格

| 方法/构造器                | 是否有外部类参数   | 外部类对象访问方式               |
| -------------------------- | ------------------ | -------------------------------- |
| `Outer$Inner(Outer outer)` | ✅ 有（构造时注入） | 初始化赋值给 `this$0`            |
| `show()`                   | ❌ 无               | 通过 `this$0` 字段间接访问外部类 |

------

## ✅ 小结一句话

> 成员内部类的非静态方法（如 `show()`）在编译后不会有外部类对象作为方法参数，
>  但会通过内部类实例中自动添加的 `this$0` 字段间接持有并访问外部类对象。

------

如果你愿意，我可以帮你展示完整的 `javap -c -p` 反编译输出（含字节码指令）并配上注释图，让你更直观看到方法调用堆栈和参数寄存器变化。是否要我生成那张对照图？

<div style="height:8px; border:none; border-radius:4px;
background:linear-gradient(to right, #ff512f, #f09819);">
</div>

这个show()没有this对象吗？成员方法不是都有个this对象作为参数吗？

👍 非常到位的问题 —— 你现在问的其实是 **Java 实例方法在字节码层面上是否真的有一个隐式的 `this` 参数**。答案是：

> ✅ **是的！每个非静态方法在 JVM 层面上都隐式带有一个参数：`this`。**
>
> 所以 `Inner.show()` 的第一个隐式参数就是当前的 `Inner` 实例对象。

------

## 🧩 我们来从 JVM 的视角看一遍

先看这段代码：

```java
public class Outer {
    private int x = 10;

    public class Inner {
        public void show() {
            System.out.println("x = " + x);
        }
    }
}
```

编译后，用命令：

```bash
javap -c -p Outer$Inner
```

输出大致如下：

```
public void show();
  Code:
     0: getstatic     #2   // Field java/lang/System.out:Ljava/io/PrintStream;
     3: aload_0             // 👈 加载 this（也就是当前 Inner 实例）
     4: getfield       #3   // Field this$0:LOuter;  // 取出外部类引用
     7: getfield       #4   // Field Outer.x:I       // 取外部类字段
    10: invokevirtual  #5   // Method java/io/PrintStream.println:(I)V
    13: return
```

------

## 🔍 逐行分析：

| 字节码             | 含义                              | 解释                                         |
| ------------------ | --------------------------------- | -------------------------------------------- |
| `aload_0`          | 加载第0号局部变量                 | 第0号局部变量永远是当前对象的引用，即 `this` |
| `getfield this$0`  | 从 `this` 对象中取出字段 `this$0` | 即外部类引用                                 |
| `getfield Outer.x` | 从外部类对象取出字段 `x`          | 访问外部类私有字段                           |
| `println`          | 调用打印方法                      | 输出结果                                     |

------

## 🧠 关键点总结：

| 概念                   | 是否存在 | 存储位置            | 说明                         |
| ---------------------- | -------- | ------------------- | ---------------------------- |
| `this`（内部类实例）   | ✅ 有     | 局部变量表第0槽位   | 每个实例方法隐式传入         |
| `this$0`（外部类引用） | ✅ 有     | 内部类对象的字段    | 构造时由编译器注入           |
| 外部类对象             | ✅ 有     | 由 `this$0` 保存    | 用于访问外部类成员           |
| 方法参数               | ❌ 无     | `show()` 没显式参数 | 因为它从 `this$0` 里取外部类 |

------

## 🧩 形象比喻：

假设你在执行：

```java
inner.show();
```

底层等价于：

```java
Outer$Inner.show(inner);
```

也就是说，JVM 层面上确实会有这样一个签名：

```java
void show(Outer$Inner this)
```

> `this` 是第一个隐式参数；
>  在 `show()` 内部访问外部类字段时，它再从 `this.this$0` 拿到外部类引用。

------

## ✅ 结论一句话：

> 成员方法在 JVM 层面总是有一个隐式参数 `this`（当前实例），
>  而成员内部类的非静态方法在此基础上，还通过 `this$0` 字段间接引用外部类对象。

------

是否希望我接下来帮你画一张 JVM 层级内存图，标出：

- `this` 在局部变量表中的位置
- `this$0` 在堆中对象结构的位置
- `this.this$0.x` 的访问路径？

那张图能把“两个 this（一个参数，一个字段）”的区别瞬间看懂。

<div style="height:8px; border:none; border-radius:4px;
background:linear-gradient(to right, #ff512f, #f09819);">
</div>

我在看arraylist迭代器源码中的next()方法时，其中有一句ArrayList.this.elementData；这是什么用法？

非常好的问题，这个细节正是 **内部类（尤其是成员内部类）访问外部类成员** 的一个“编译器语法糖”体现。
 你在 `ArrayList` 的迭代器源码里看到的那句：

```java
ArrayList.this.elementData
```

其实是 **内部类访问外部类对象字段** 的一种写法，编译器自动为你完成“跳转”到外部实例。
 我们来深入剖析一下 👇

------

## 🧩 一、背景：ArrayList 的迭代器是一个成员内部类

JDK 中 `ArrayList` 的简化结构如下：

```java
public class ArrayList<E> {
    transient Object[] elementData; // 存放实际元素的数组
    private int size;

    public Iterator<E> iterator() {
        return new Itr(); // 返回内部类实例
    }

    private class Itr implements Iterator<E> {
        int cursor; // 下一个要返回的元素索引
        int lastRet = -1;

        public E next() {
            int i = cursor;
            Object[] elementData = ArrayList.this.elementData; // 👈 关键
            if (i >= size)
                throw new NoSuchElementException();
            cursor = i + 1;
            return (E) elementData[lastRet = i];
        }
    }
}
```

------

## 🧠 二、这句代码的真正含义

```java
ArrayList.this.elementData
```

表示：

> **取出当前 `Itr` 对象所属的外部 `ArrayList` 实例的 `elementData` 字段。**

换句话说：

- `ArrayList.this`：是外部类 `ArrayList` 的实例引用；
- `.elementData`：访问该外部类实例的字段。

这相当于字节码层面的：

```java
this.this$0.elementData
```

------

## 🧩 三、为什么需要显式写成 `ArrayList.this`？

因为在 `Itr` 这个内部类中：

- 既有 `this`（当前迭代器对象）
- 又有 `ArrayList.this`（外部 ArrayList 对象）

👉 如果直接写 `this.elementData`，会访问不到（因为 `Itr` 自己没有 `elementData` 字段）。

所以必须显式告诉编译器：

> “我要访问外层的 `ArrayList` 实例的字段，不是当前内部类的字段。”

------

## ⚙️ 四、编译器视角（反编译）

编译后 `Itr` 类中其实长这样：

```java
class ArrayList$Itr implements Iterator {
    final ArrayList this$0; // 👈 编译器自动添加的外部类引用

    ArrayList$Itr(ArrayList outer) {
        this.this$0 = outer;
    }

    public Object next() {
        Object[] elementData = this.this$0.elementData; // 👈 这就是 ArrayList.this.elementData
        ...
    }
}
```

------

## 🧩 五、总结对照表

| 表达式           | 含义                       | 所属对象    |
| ---------------- | -------------------------- | ----------- |
| `this`           | 当前内部类实例             | `Itr`       |
| `ArrayList.this` | 外部类实例引用             | `ArrayList` |
| `this.this$0`    | 编译器生成的外部类引用字段 | `ArrayList` |

------

## ✅ 结论一句话：

> 在成员内部类中，`OuterClass.this` 表示“当前内部类对象所属的外部类实例”。
>
> 因此 `ArrayList.this.elementData` 的意思就是：
>
> “访问当前迭代器所属的那个 ArrayList 的 elementData 数组”。

------

如果你想，我可以帮你画出一个简化的对象图，用箭头展示：

- `Itr` 对象中保存的 `this$0 → ArrayList` 引用；
- `ArrayList.this.elementData` 实际对应的内存访问路径。

要我帮你画出来吗？