dup指令有什么用？例如为什么执行完new #2,然后就是 dup，此时在操作数栈中为啥要有两个对象指针？

非常棒！👏 你现在的问题已经完全进入 **JVM 字节码执行模型层面**，这正是理解类加载、对象创建与初始化流程的核心。
 你的问题可以归结为：

> “为什么在 `new` 之后需要 `dup`？为什么要把对象引用复制一份放到操作数栈上？”

我们来**一步步可视化**地解释。

------

## 🧩 一、先看经典的例子

```java
User user = new User();
```

编译成字节码（用 `javap -v` 看）大致是：

```
0: new           #2 <User>        // 创建对象
3: dup                              // 复制对象引用
4: invokespecial #3 <User.<init>>  // 调用构造器
7: astore_1                         // 存入局部变量表 slot 1
```

------

## 🧠 二、理解 `new` 指令：只是“分配内存”

`new` 的作用：

> 在堆上分配一块内存空间，用于存放对象实例，并返回一个**未初始化的引用**到操作数栈。

执行完 `new #2` 后，栈中是这样：

```
操作数栈顶 → [对象引用A]   （此时仅分配了内存，还未执行构造函数）
```

------

## ⚙️ 三、为什么要立刻执行 `dup`

接下来我们需要调用构造方法 `<init>`：

```java
invokespecial #3 <User.<init>>
```

而调用构造器时，JVM 需要两个操作数：

1. **方法接收者（this）引用**；
2. （可选）构造器的参数。

------

### 问题：`invokespecial` 会**消费掉栈顶的对象引用**

假设我们不执行 `dup`，直接：

```
new #2        → 栈顶 [A]
invokespecial → 栈顶空了（A 被弹出传给 <init>）
astore_1      → ❌ 没对象可存
```

此时对象引用被 `<init>` 用掉了，栈顶已经没了那份引用，**无法再保存到变量中**。

------

## ✅ 四、dup 的作用

`dup` 指令的语义是：

> 复制操作数栈顶的值，并把副本再压回栈顶。

所以执行顺序与栈变化如下👇

| 指令            | 操作数栈内容（栈顶在右）                          |
| --------------- | ------------------------------------------------- |
| `new #2`        | [A]                                               |
| `dup`           | [A, A]                                            |
| `invokespecial` | 调用 `<init>` 消耗掉一个 A（作为 this）→ 剩下 [A] |
| `astore_1`      | 把 A 存到局部变量表 slot1                         |

✅ 最终局部变量表里保存了那份 `A` 引用。

------

## 📦 五、完整执行路径图

```
0: new #2           // 在堆中分配对象A，压入引用A
   [A]
3: dup              // 复制引用A，再压入栈
   [A, A]
4: invokespecial    // 调用构造器，用掉一个A（作为this）
   [A]
7: astore_1         // 保存剩下的A到局部变量表
   []
```

**至此：**

- 对象 A 完成初始化；
- 局部变量 `user` 持有它的引用。

------

## 🧠 六、`dup` 的字节码语义

`dup` 的规范定义（《Java Virtual Machine Spec §6.5.dup》）：

> **dup**
>  Duplicate the value on the top of the operand stack and push the duplicated value onto the operand stack.

| 指令   | 栈变化                                                      | 含义                      |
| ------ | ----------------------------------------------------------- | ------------------------- |
| `dup`  | `..., value → ..., value, value`                            | 复制栈顶单槽元素          |
| `dup2` | `..., value1, value2 → ..., value1, value2, value1, value2` | 复制两个槽（long/double） |

------

## 🧩 七、如果对象有构造函数参数呢？

例如：

```java
User user = new User("Tom");
```

字节码：

```
0: new           #2 <User>
3: dup
4: ldc           #3 "Tom"
6: invokespecial #4 <User.<init>(Ljava/lang/String;)V>
9: astore_1
```

调用 `<init>` 前要先把 `"Tom"` 压栈；
 但 `dup` 仍然要在前面保证**有一份对象引用**留给后续 `astore_1` 使用。

------

## 🧩 八、总结一句话

| 指令            | 作用                                   |
| --------------- | -------------------------------------- |
| `new`           | 在堆上创建未初始化对象，返回引用       |
| `dup`           | 复制对象引用，保证构造函数调用后还能用 |
| `invokespecial` | 调用构造器，用掉一份引用               |
| `astore`        | 存储剩下的那份引用到局部变量表         |

**因此：**

> `dup` 的存在是为了让构造函数调用后，仍然有一个对象引用留在栈上用于后续赋值。
>  它是 JVM 在生成字节码时自动插入的“引用备份机制”。

------

如果你想，我可以给你画一张「操作数栈变化示意图」📊，
 展示从 `new` → `dup` → `invokespecial` → `astore` 的每一步栈状态变化（类似 HotSpot interpreter stacktrace 视图）。
 要我画这张图吗？